pythorvision/__init__.py
pythorvision/camera.py
pythorvision/client.py
pythorvision/video.py
pythorvision-0.3.0.dist-info/licenses/LICENSE.txt
pythorvision-0.3.0.dist-info/METADATA
pythorvision-0.3.0.dist-info/WHEEL
pythorvision-0.3.0.dist-info/top_level.txt
pythorvision-0.3.0.dist-info/RECORD
