Metadata-Version: 2.4
Name: pythorvision
Version: 0.3.0
Summary: Python API for ThorVision
Author-email: Kontex <hhuang@kontex.com>
License: MIT License
Keywords: vision,camera,api
Requires-Python: >=3.6
License-File: LICENSE.txt
Requires-Dist: requests>=2.25.0
Requires-Dist: pydantic>=2.0
Requires-Dist: numpy
Requires-Dist: av
Dynamic: license-file
